{
  "repositories": [
    {
      "author": "nhsuk",
      "name": "nhsuk-frontend",
      "href": "https://github.com/nhsuk/nhsuk-frontend",
      "description": "NHS.UK frontend library - in prerelease for use in prototypes and testing",
      "language": "CSS",
      "stars": 301,
      "forks": 21
    },
    {
      "author": "nostalgic-css",
      "name": "NES.css",
      "href": "https://github.com/nostalgic-css/NES.css",
      "description": "NES-style CSS Framework | ファミコン風CSSフレームワーク",
      "language": "CSS",
      "stars": 8403,
      "forks": 667
    },
    {
      "author": "twbs",
      "name": "bootstrap",
      "href": "https://github.com/twbs/bootstrap",
      "description": "The most popular HTML, CSS, and JavaScript framework for developing responsive, mobile first projects on the web.",
      "language": "CSS",
      "stars": 129515,
      "forks": 63643
    },
    {
      "author": "iann0036",
      "name": "AWSConsoleRecorder",
      "href": "https://github.com/iann0036/AWSConsoleRecorder",
      "description": "Records actions made in the AWS Management Console and outputs the equivalent CLI/SDK commands and CloudFormation/Terraform templates.",
      "language": "CSS",
      "stars": 139,
      "forks": 5
    },
    {
      "author": "filamentgroup",
      "name": "select-css",
      "href": "https://github.com/filamentgroup/select-css",
      "description": "Cross-browser styles for consistent select element styling",
      "language": "CSS",
      "stars": 861,
      "forks": 75
    },
    {
      "author": "tailwindcss",
      "name": "tailwindcss",
      "href": "https://github.com/tailwindcss/tailwindcss",
      "description": "A utility-first CSS framework for rapid UI development.",
      "language": "CSS",
      "stars": 8193,
      "forks": 389
    },
    {
      "author": "jgthms",
      "name": "bulma",
      "href": "https://github.com/jgthms/bulma",
      "description": "Modern CSS framework based on Flexbox",
      "language": "CSS",
      "stars": 31884,
      "forks": 2510
    },
    {
      "author": "nakov",
      "name": "Practical-Cryptography-for-Developers-Book",
      "href": "https://github.com/nakov/Practical-Cryptography-for-Developers-Book",
      "description": "Practical Cryptography for Developers: Hashes, MAC, Key Derivation, DHKE, Symmetric and Asymmetric Ciphers, Public Key Cryptosystems, RSA, Elliptic Curves, ECC, secp256k1, ECDH, ECIES, Digital Signatures, ECDSA, EdDSA",
      "language": "CSS",
      "stars": 1071,
      "forks": 73
    },
    {
      "author": "rstacruz",
      "name": "cheatsheets",
      "href": "https://github.com/rstacruz/cheatsheets",
      "description": "My cheatsheets",
      "language": "CSS",
      "stars": 5112,
      "forks": 1073
    },
    {
      "author": "picturepan2",
      "name": "spectre",
      "href": "https://github.com/picturepan2/spectre",
      "description": "Spectre.css - A Lightweight, Responsive and Modern CSS Framework",
      "language": "CSS",
      "stars": 8752,
      "forks": 603
    },
    {
      "author": "StylishThemes",
      "name": "GitHub-Dark",
      "href": "https://github.com/StylishThemes/GitHub-Dark",
      "description": "Dark GitHub style",
      "language": "CSS",
      "stars": 3720,
      "forks": 284
    },
    {
      "author": "theme-next",
      "name": "hexo-theme-next",
      "href": "https://github.com/theme-next/hexo-theme-next",
      "description": "Elegant and powerful theme for Hexo.",
      "language": "CSS",
      "stars": 1909,
      "forks": 587
    },
    {
      "author": "Requarks",
      "name": "wiki",
      "href": "https://github.com/Requarks/wiki",
      "description": "Wiki.js | A modern, lightweight and powerful wiki app built on Node.js",
      "language": "CSS",
      "stars": 3548,
      "forks": 509
    },
    {
      "author": "CodyHouse",
      "name": "codyhouse-framework",
      "href": "https://github.com/CodyHouse/codyhouse-framework",
      "description": "Create your design system.",
      "language": "CSS",
      "stars": 216,
      "forks": 26
    },
    {
      "author": "sharu725",
      "name": "online-cv",
      "href": "https://github.com/sharu725/online-cv",
      "description": "A minimal Jekyll Theme to host your resume (CV)",
      "language": "CSS",
      "stars": 671,
      "forks": 1188
    },
    {
      "author": "AnomalyInnovations",
      "name": "serverless-stack-com",
      "href": "https://github.com/AnomalyInnovations/serverless-stack-com",
      "description": "Source for Serverless-Stack.com",
      "language": "CSS",
      "stars": 1666,
      "forks": 176
    },
    {
      "author": "uikit",
      "name": "uikit",
      "href": "https://github.com/uikit/uikit",
      "description": "A lightweight and modular front-end framework for developing fast and powerful web interfaces",
      "language": "CSS",
      "stars": 13622,
      "forks": 2027
    },
    {
      "author": "carloscuesta",
      "name": "gitmoji",
      "href": "https://github.com/carloscuesta/gitmoji",
      "description": "An emoji guide for your commit messages. 😜",
      "language": "CSS",
      "stars": 4290,
      "forks": 252
    },
    {
      "author": "Microsoft",
      "name": "vscode-docs",
      "href": "https://github.com/Microsoft/vscode-docs",
      "description": "Public documentation for Visual Studio Code",
      "language": "CSS",
      "stars": 1824,
      "forks": 1567
    },
    {
      "author": "adobe",
      "name": "spectrum-css",
      "href": "https://github.com/adobe/spectrum-css",
      "description": "The standard CSS implementation of the Spectrum design language.",
      "language": "CSS",
      "stars": 82,
      "forks": 10
    },
    {
      "author": "LiangJunrong",
      "name": "document-library",
      "href": "https://github.com/LiangJunrong/document-library",
      "description": "jsliang 的文档库. 里面包含了所有的前端文章，例如 vue、react,、angular、微信小程序、设计模式等……",
      "language": "CSS",
      "stars": 411,
      "forks": 59
    },
    {
      "author": "framework7io",
      "name": "framework7",
      "href": "https://github.com/framework7io/framework7",
      "description": "Full featured HTML framework for building iOS & Android apps",
      "language": "CSS",
      "stars": 13553,
      "forks": 2869
    },
    {
      "author": "justinmeiners",
      "name": "lc3-vm",
      "href": "https://github.com/justinmeiners/lc3-vm",
      "description": "Write your own virtual machine for the LC-3 computer!",
      "language": "CSS",
      "stars": 91,
      "forks": 11
    },
    {
      "author": "nrandecker",
      "name": "particle",
      "href": "https://github.com/nrandecker/particle",
      "description": "A simple portfolio Jekyll theme:",
      "language": "CSS",
      "stars": 361,
      "forks": 686
    },
    {
      "author": "pages-themes",
      "name": "cayman",
      "href": "https://github.com/pages-themes/cayman",
      "description": "Cayman is a Jekyll theme for GitHub Pages",
      "language": "CSS",
      "stars": 401,
      "forks": 1121
    }
  ]
}