{
  "repositories": [
    {
      "author": "microsoft",
      "name": "TypeScript-Node-Starter",
      "href": "https://github.com/microsoft/TypeScript-Node-Starter",
      "description": "A starter template for TypeScript and Node with a detailed README describing how to use the two together.",
      "language": "CSS",
      "stars": 0,
      "forks": 1717,
      "starsInPeriod": 3
    },
    {
      "author": "Hacker0x01",
      "name": "hacker101",
      "href": "https://github.com/Hacker0x01/hacker101",
      "description": "Hacker101",
      "language": "CSS",
      "stars": 0,
      "forks": 1560,
      "starsInPeriod": 6
    },
    {
      "author": "vinceliuice",
      "name": "Mojave-gtk-theme",
      "href": "https://github.com/vinceliuice/Mojave-gtk-theme",
      "description": "Mojave is a macos Mojave like theme for GTK 3, GTK 2 and Gnome-Shell",
      "language": "CSS",
      "stars": 0,
      "forks": 177,
      "starsInPeriod": 6
    },
    {
      "author": "AnomalyInnovations",
      "name": "serverless-stack-com",
      "href": "https://github.com/AnomalyInnovations/serverless-stack-com",
      "description": "Source for Serverless-Stack.com",
      "language": "CSS",
      "stars": 0,
      "forks": 327,
      "starsInPeriod": 3
    },
    {
      "author": "pages-themes",
      "name": "cayman",
      "href": "https://github.com/pages-themes/cayman",
      "description": "Cayman is a Jekyll theme for GitHub Pages",
      "language": "CSS",
      "stars": 0,
      "forks": 1578,
      "starsInPeriod": 0
    },
    {
      "author": "bjmashibing",
      "name": "InternetArchitect",
      "href": "https://github.com/bjmashibing/InternetArchitect",
      "description": "年薪百万互联网架构师课程文档及源码(公开部分)",
      "language": "CSS",
      "stars": 0,
      "forks": 312,
      "starsInPeriod": 3
    },
    {
      "author": "m4heshd",
      "name": "whatsapp-desktop-dark",
      "href": "https://github.com/m4heshd/whatsapp-desktop-dark",
      "description": "Dark mode for WhatsApp desktop official version (Windows & macOS)",
      "language": "CSS",
      "stars": 0,
      "forks": 66,
      "starsInPeriod": 4
    },
    {
      "author": "jekyll",
      "name": "minima",
      "href": "https://github.com/jekyll/minima",
      "description": "Minima is a one-size-fits-all Jekyll theme for writers.",
      "language": "CSS",
      "stars": 0,
      "forks": 1666,
      "starsInPeriod": 4
    },
    {
      "author": "tailwindcss",
      "name": "designing-with-tailwindcss",
      "href": "https://github.com/tailwindcss/designing-with-tailwindcss",
      "description": "Source code for the \"Designing with Tailwind CSS\" course.",
      "language": "CSS",
      "stars": 0,
      "forks": 143,
      "starsInPeriod": 0
    },
    {
      "author": "heathermiller",
      "name": "dist-prog-book",
      "href": "https://github.com/heathermiller/dist-prog-book",
      "description": null,
      "language": "CSS",
      "stars": 0,
      "forks": 242,
      "starsInPeriod": 93
    },
    {
      "author": "hiromis",
      "name": "notes",
      "href": "https://github.com/hiromis/notes",
      "description": null,
      "language": "CSS",
      "stars": 0,
      "forks": 447,
      "starsInPeriod": 3
    },
    {
      "author": "RedSpider1",
      "name": "concurrent",
      "href": "https://github.com/RedSpider1/concurrent",
      "description": "这是RedSpider社区成员原创与维护的Java多线程系列文章。",
      "language": "CSS",
      "stars": 0,
      "forks": 21,
      "starsInPeriod": 25
    },
    {
      "author": "cobidev",
      "name": "simplefolio",
      "href": "https://github.com/cobidev/simplefolio",
      "description": "⚡️ A minimal portfolio template for Developers",
      "language": "CSS",
      "stars": 0,
      "forks": 682,
      "starsInPeriod": 23
    },
    {
      "author": "alshedivat",
      "name": "al-folio",
      "href": "https://github.com/alshedivat/al-folio",
      "description": "A beautiful Jekyll theme for academics",
      "language": "CSS",
      "stars": 0,
      "forks": 683,
      "starsInPeriod": 2
    },
    {
      "author": "IanLunn",
      "name": "Hover",
      "href": "https://github.com/IanLunn/Hover",
      "description": "A collection of CSS3 powered hover effects to be applied to links, buttons, logos, SVG, featured images and so on. Easily apply to your own elements, modify or just use for inspiration. Available in CSS, Sass, and LESS.",
      "language": "CSS",
      "stars": 0,
      "forks": 4931,
      "starsInPeriod": 6
    },
    {
      "author": "BNDong",
      "name": "Cnblogs-Theme-SimpleMemory",
      "href": "https://github.com/BNDong/Cnblogs-Theme-SimpleMemory",
      "description": "🍭 Cnblogs theme / Basic theme : SimpleMemory",
      "language": "CSS",
      "stars": 0,
      "forks": 486,
      "starsInPeriod": 4
    },
    {
      "author": "khronokernel",
      "name": "Opencore-Vanilla-Desktop-Guide",
      "href": "https://github.com/khronokernel/Opencore-Vanilla-Desktop-Guide",
      "description": "Host for files for the OpenCore Vanilla Desktop Guide",
      "language": "CSS",
      "stars": 0,
      "forks": 60,
      "starsInPeriod": 5
    },
    {
      "author": "godotengine",
      "name": "godot-docs",
      "href": "https://github.com/godotengine/godot-docs",
      "description": "Godot Engine official documentation",
      "language": "CSS",
      "stars": 0,
      "forks": 1197,
      "starsInPeriod": 0
    },
    {
      "author": "ryanoasis",
      "name": "nerd-fonts",
      "href": "https://github.com/ryanoasis/nerd-fonts",
      "description": "Iconic font aggregator, collection, & patcher. 3,600+ icons, 50+ patched fonts: Hack, Source Code Pro, more. Glyph collections: Font Awesome, Material Design Icons, Octicons, & more",
      "language": "CSS",
      "stars": 0,
      "forks": 1391,
      "starsInPeriod": 21
    },
    {
      "author": "TryGhost",
      "name": "Casper",
      "href": "https://github.com/TryGhost/Casper",
      "description": "The default personal blogging theme for Ghost",
      "language": "CSS",
      "stars": 0,
      "forks": 2175,
      "starsInPeriod": 2
    },
    {
      "author": "pages-themes",
      "name": "minimal",
      "href": "https://github.com/pages-themes/minimal",
      "description": "Minimal is a Jekyll theme for GitHub Pages",
      "language": "CSS",
      "stars": 0,
      "forks": 1483,
      "starsInPeriod": 0
    },
    {
      "author": "LineageOS",
      "name": "lineage_wiki",
      "href": "https://github.com/LineageOS/lineage_wiki",
      "description": null,
      "language": "CSS",
      "stars": 0,
      "forks": 353,
      "starsInPeriod": 0
    },
    {
      "author": "alphardex",
      "name": "aqua.css",
      "href": "https://github.com/alphardex/aqua.css",
      "description": "为美好的CSS世界献上祝福！",
      "language": "CSS",
      "stars": 0,
      "forks": 5,
      "starsInPeriod": 9
    },
    {
      "author": "OssamaRafique",
      "name": "Corona-Statistics-And-Tracker-Dashboard-Angular-9",
      "href": "https://github.com/OssamaRafique/Corona-Statistics-And-Tracker-Dashboard-Angular-9",
      "description": "🦠Corona Virus / Covid 19 Tracker Dashboard With Awesome UI + PWA + NodeJS Scraper",
      "language": "CSS",
      "stars": 0,
      "forks": 51,
      "starsInPeriod": 8
    },
    {
      "author": "mmistakes",
      "name": "minimal-mistakes",
      "href": "https://github.com/mmistakes/minimal-mistakes",
      "description": "📐 Jekyll theme for building a personal site, blog, project documentation, or portfolio.",
      "language": "CSS",
      "stars": 0,
      "forks": 10696,
      "starsInPeriod": 3
    }
  ]
}