{
  "repositories": [
    {
      "author": "tweag",
      "name": "asterius",
      "href": "https://github.com/tweag/asterius",
      "description": "A Haskell to WebAssembly compiler",
      "language": "Haskell",
      "stars": 168,
      "forks": 4
    },
    {
      "author": "koalaman",
      "name": "shellcheck",
      "href": "https://github.com/koalaman/shellcheck",
      "description": "ShellCheck, a static analysis tool for shell scripts",
      "language": "Haskell",
      "stars": 11245,
      "forks": 585
    },
    {
      "author": "input-output-hk",
      "name": "cardano-sl",
      "href": "https://github.com/input-output-hk/cardano-sl",
      "description": "Cryptographic currency implementing Ouroboros PoS protocol",
      "language": "Haskell",
      "stars": 2594,
      "forks": 413
    },
    {
      "author": "jgm",
      "name": "pandoc",
      "href": "https://github.com/jgm/pandoc",
      "description": "Universal markup converter",
      "language": "Haskell",
      "stars": 11743,
      "forks": 1381
    },
    {
      "author": "PostgREST",
      "name": "postgrest",
      "href": "https://github.com/PostgREST/postgrest",
      "description": "REST API for any Postgres database",
      "language": "Haskell",
      "stars": 10833,
      "forks": 478
    },
    {
      "author": "nikita-volkov",
      "name": "refined",
      "href": "https://github.com/nikita-volkov/refined",
      "description": "Refinement types with static and runtime checking",
      "language": "Haskell",
      "stars": 51,
      "forks": 5
    },
    {
      "author": "dmjio",
      "name": "miso",
      "href": "https://github.com/dmjio/miso",
      "description": "🍜 A tasty Haskell front-end framework",
      "language": "Haskell",
      "stars": 936,
      "forks": 66
    },
    {
      "author": "yav",
      "name": "graphmod",
      "href": "https://github.com/yav/graphmod",
      "description": "A utility for displaying the module dependencies of Haskell programs.",
      "language": "Haskell",
      "stars": 71,
      "forks": 13
    },
    {
      "author": "ngless-toolkit",
      "name": "ngless",
      "href": "https://github.com/ngless-toolkit/ngless",
      "description": "NGLess: NGS with less work",
      "language": "Haskell",
      "stars": 52,
      "forks": 11
    },
    {
      "author": "input-output-hk",
      "name": "iohk-ops",
      "href": "https://github.com/input-output-hk/iohk-ops",
      "description": "NixOps deployment configuration for IOHK devops",
      "language": "Haskell",
      "stars": 65,
      "forks": 24
    },
    {
      "author": "elm",
      "name": "package.elm-lang.org",
      "href": "https://github.com/elm/package.elm-lang.org",
      "description": "website for browsing packages and exploring documentation",
      "language": "Haskell",
      "stars": 134,
      "forks": 70
    },
    {
      "author": "reflex-frp",
      "name": "reflex-dom-contrib",
      "href": "https://github.com/reflex-frp/reflex-dom-contrib",
      "description": null,
      "language": "Haskell",
      "stars": 34,
      "forks": 26
    },
    {
      "author": "purescript",
      "name": "purescript",
      "href": "https://github.com/purescript/purescript",
      "description": "A strongly-typed language that compiles to Javascript",
      "language": "Haskell",
      "stars": 4810,
      "forks": 375
    },
    {
      "author": "elm",
      "name": "compiler",
      "href": "https://github.com/elm/compiler",
      "description": "Compiler for Elm, a functional language for reliable webapps.",
      "language": "Haskell",
      "stars": 4555,
      "forks": 335
    },
    {
      "author": "facebook",
      "name": "Haxl",
      "href": "https://github.com/facebook/Haxl",
      "description": "A Haskell library that simplifies access to remote data, such as databases or web-based services.",
      "language": "Haskell",
      "stars": 3170,
      "forks": 266
    },
    {
      "author": "commercialhaskell",
      "name": "stack",
      "href": "https://github.com/commercialhaskell/stack",
      "description": "The Haskell Tool Stack",
      "language": "Haskell",
      "stars": 2713,
      "forks": 580
    },
    {
      "author": "idris-lang",
      "name": "Idris-dev",
      "href": "https://github.com/idris-lang/Idris-dev",
      "description": "A Dependently Typed Functional Programming Language",
      "language": "Haskell",
      "stars": 2432,
      "forks": 575
    },
    {
      "author": "data61",
      "name": "fp-course",
      "href": "https://github.com/data61/fp-course",
      "description": "Functional Programming Course",
      "language": "Haskell",
      "stars": 2272,
      "forks": 878
    },
    {
      "author": "caiorss",
      "name": "Functional-Programming",
      "href": "https://github.com/caiorss/Functional-Programming",
      "description": "Functional Programming concepts, examples and patterns illustrated in Haskell, Ocaml and Python",
      "language": "Haskell",
      "stars": 2257,
      "forks": 120
    },
    {
      "author": "luna",
      "name": "luna",
      "href": "https://github.com/luna/luna",
      "description": "Hybrid textual and visual functional programming.",
      "language": "Haskell",
      "stars": 2232,
      "forks": 55
    },
    {
      "author": "carp-lang",
      "name": "Carp",
      "href": "https://github.com/carp-lang/Carp",
      "description": "A statically typed lisp, without a GC, for real-time applications.",
      "language": "Haskell",
      "stars": 2135,
      "forks": 77
    },
    {
      "author": "sdiehl",
      "name": "write-you-a-haskell",
      "href": "https://github.com/sdiehl/write-you-a-haskell",
      "description": "Building a modern functional compiler from first principles. (http://dev.stephendiehl.com/fun/)",
      "language": "Haskell",
      "stars": 2058,
      "forks": 167
    },
    {
      "author": "ghcjs",
      "name": "ghcjs",
      "href": "https://github.com/ghcjs/ghcjs",
      "description": "Haskell to JavaScript compiler, based on GHC",
      "language": "Haskell",
      "stars": 1948,
      "forks": 143
    },
    {
      "author": "yesodweb",
      "name": "yesod",
      "href": "https://github.com/yesodweb/yesod",
      "description": "A RESTful Haskell web framework built on WAI.",
      "language": "Haskell",
      "stars": 1933,
      "forks": 315
    },
    {
      "author": "ghc",
      "name": "ghc",
      "href": "https://github.com/ghc/ghc",
      "description": "Mirror of the Glasgow Haskell Compiler. Patches are best submitted to GHC's Phabricator (https://phabricator.haskell.org/), bugs and feature-requests are best filed to GHC's Trac (https://ghc.haskell.org/trac/ghc), or sent to the mailing list (ghc-devs@haskell.org). First time contributors are encouraged to get started by just sending a Pull Req…",
      "language": "Haskell",
      "stars": 1863,
      "forks": 513
    }
  ]
}