{
  "repositories": [
    {
      "author": "frk1",
      "name": "hazedumper",
      "href": "https://github.com/frk1/hazedumper",
      "description": "up to date csgo offsets and hazedumper config",
      "language": "Visual Basic",
      "stars": 472,
      "forks": 272,
      "starsInPeriod": 0
    },
    {
      "author": "AliBawazeEer",
      "name": "RAT-NjRat-0.7d-modded-source-code",
      "href": "https://github.com/AliBawazeEer/RAT-NjRat-0.7d-modded-source-code",
      "description": "NJR",
      "language": "Visual Basic",
      "stars": 132,
      "forks": 111,
      "starsInPeriod": 1
    },
    {
      "author": "NHLGames",
      "name": "NHLGames",
      "href": "https://github.com/NHLGames/NHLGames",
      "description": "Windows front end for watching NHL games",
      "language": "Visual Basic",
      "stars": 160,
      "forks": 41,
      "starsInPeriod": 0
    },
    {
      "author": "ultrara1n",
      "name": "MiToolkit",
      "href": "https://github.com/ultrara1n/MiToolkit",
      "description": "Tool um die MiHome App und die Vacuum Erweiterung auf Deutsch zu übersetzen.",
      "language": "Visual Basic",
      "stars": 70,
      "forks": 14,
      "starsInPeriod": 0
    }
  ]
}