{
  "repositories": [
    {
      "author": "s-macke",
      "name": "Interplanetary-Postal-Service",
      "href": "https://github.com/s-macke/Interplanetary-Postal-Service",
      "description": "Lunar lander type game with complex fluid dynamics",
      "language": "C",
      "stars": 337,
      "forks": 8
    },
    {
      "author": "torvalds",
      "name": "linux",
      "href": "https://github.com/torvalds/linux",
      "description": "Linux kernel source tree",
      "language": "C",
      "stars": 63107,
      "forks": 22998
    },
    {
      "author": "raspberrypi",
      "name": "linux",
      "href": "https://github.com/raspberrypi/linux",
      "description": "Kernel source tree for Raspberry Pi Foundation-provided kernel builds. Issues unrelated to the linux kernel should be posted on the community forum at https://www.raspberrypi.org/forum",
      "language": "C",
      "stars": 4957,
      "forks": 2552
    },
    {
      "author": "vim",
      "name": "vim",
      "href": "https://github.com/vim/vim",
      "description": "The official Vim repository",
      "language": "C",
      "stars": 14081,
      "forks": 1786
    },
    {
      "author": "antirez",
      "name": "redis",
      "href": "https://github.com/antirez/redis",
      "description": "Redis is an in-memory database that persists on disk. The data model is key-value, but many different kind of values are supported: Strings, Lists, Sets, Sorted Sets, Hashes, HyperLogLogs, Bitmaps.",
      "language": "C",
      "stars": 31587,
      "forks": 12133
    },
    {
      "author": "DoubleLabyrinth",
      "name": "navicat-keygen",
      "href": "https://github.com/DoubleLabyrinth/navicat-keygen",
      "description": "A keygen for Navicat Premium",
      "language": "C",
      "stars": 1927,
      "forks": 542
    },
    {
      "author": "p-gen",
      "name": "smenu",
      "href": "https://github.com/p-gen/smenu",
      "description": "Terminal utility that allows you to use words coming from the standard input to create a nice selection window just below the cursor. Once done, your selection will be sent to standard output. More in the Wiki",
      "language": "C",
      "stars": 1296,
      "forks": 24
    },
    {
      "author": "curl",
      "name": "curl",
      "href": "https://github.com/curl/curl",
      "description": "A command line tool and library for transferring data with URL syntax, supporting HTTP, HTTPS, FTP, FTPS, GOPHER, TFTP, SCP, SFTP, SMB, TELNET, DICT, LDAP, LDAPS, FILE, IMAP, SMTP, POP3, RTSP and RTMP. libcurl offers a myriad of powerful features",
      "language": "C",
      "stars": 9518,
      "forks": 2527
    },
    {
      "author": "commaai",
      "name": "openpilot",
      "href": "https://github.com/commaai/openpilot",
      "description": "open source driving agent",
      "language": "C",
      "stars": 8307,
      "forks": 2021
    },
    {
      "author": "php",
      "name": "php-src",
      "href": "https://github.com/php/php-src",
      "description": "The PHP Interpreter",
      "language": "C",
      "stars": 19375,
      "forks": 4987
    },
    {
      "author": "felix-lang",
      "name": "felix",
      "href": "https://github.com/felix-lang/felix",
      "description": "The Felix Programming Language",
      "language": "C",
      "stars": 448,
      "forks": 28
    },
    {
      "author": "trunkmaster",
      "name": "nextspace",
      "href": "https://github.com/trunkmaster/nextspace",
      "description": "NeXTSTEP-like desktop environment for Linux",
      "language": "C",
      "stars": 48,
      "forks": 3
    },
    {
      "author": "imbushuo",
      "name": "mac-precision-touchpad",
      "href": "https://github.com/imbushuo/mac-precision-touchpad",
      "description": "Windows Precision Touchpad Driver Implementation for Apple MacBook / Magic Trackpad",
      "language": "C",
      "stars": 600,
      "forks": 33
    },
    {
      "author": "slimbootloader",
      "name": "slimbootloader",
      "href": "https://github.com/slimbootloader/slimbootloader",
      "description": "Visit http://slimbootloader.github.io for documentation",
      "language": "C",
      "stars": 42,
      "forks": 7
    },
    {
      "author": "firehol",
      "name": "netdata",
      "href": "https://github.com/firehol/netdata",
      "description": "Get control of your servers. Simple. Effective. Awesome! https://my-netdata.io/",
      "language": "C",
      "stars": 31831,
      "forks": 2697
    },
    {
      "author": "andreiw",
      "name": "RaspberryPiPkg",
      "href": "https://github.com/andreiw/RaspberryPiPkg",
      "description": "64-bit Tiano Core UEFI for the Raspberry Pi 3 (with devices, Linux, FreeBSD and Windows on Arm!)",
      "language": "C",
      "stars": 391,
      "forks": 60
    },
    {
      "author": "cfenollosa",
      "name": "os-tutorial",
      "href": "https://github.com/cfenollosa/os-tutorial",
      "description": "How to create an OS from scratch",
      "language": "C",
      "stars": 1850,
      "forks": 346
    },
    {
      "author": "numpy",
      "name": "numpy",
      "href": "https://github.com/numpy/numpy",
      "description": "Numpy main repository",
      "language": "C",
      "stars": 8151,
      "forks": 2992
    },
    {
      "author": "nginx",
      "name": "nginx",
      "href": "https://github.com/nginx/nginx",
      "description": "An official read-only mirror of http://hg.nginx.org/nginx/ which is updated hourly. Pull requests on GitHub cannot be accepted and will be automatically closed. The proper way to submit changes to nginx is via the nginx development mailing list, see http://nginx.org/en/docs/contributing_changes.html",
      "language": "C",
      "stars": 6786,
      "forks": 2672
    },
    {
      "author": "SoloKeysSec",
      "name": "solo",
      "href": "https://github.com/SoloKeysSec/solo",
      "description": "FIDO2 USB+NFC token optimized for security, extensibility, and style",
      "language": "C",
      "stars": 44,
      "forks": 2
    },
    {
      "author": "shadowsocks",
      "name": "shadowsocks-libev",
      "href": "https://github.com/shadowsocks/shadowsocks-libev",
      "description": "libev port of shadowsocks",
      "language": "C",
      "stars": 8926,
      "forks": 4927
    },
    {
      "author": "MarlinFirmware",
      "name": "Marlin",
      "href": "https://github.com/MarlinFirmware/Marlin",
      "description": "Optimized firmware for RepRap 3D printers based on the Arduino platform.",
      "language": "C",
      "stars": 4262,
      "forks": 5977
    },
    {
      "author": "timescale",
      "name": "timescaledb",
      "href": "https://github.com/timescale/timescaledb",
      "description": "An open-source time-series database optimized for fast ingest and complex queries. Engineered up from PostgreSQL, packaged as an extension.",
      "language": "C",
      "stars": 5530,
      "forks": 269
    },
    {
      "author": "kovidgoyal",
      "name": "kitty",
      "href": "https://github.com/kovidgoyal/kitty",
      "description": "A cross-platform, fast, feature full, GPU based terminal emulator",
      "language": "C",
      "stars": 4831,
      "forks": 202
    },
    {
      "author": "git",
      "name": "git",
      "href": "https://github.com/git/git",
      "description": "Git Source Code Mirror - This is a publish-only repository and all pull requests are ignored. Please follow Documentation/SubmittingPatches procedure for any of your improvements.",
      "language": "C",
      "stars": 24100,
      "forks": 13997
    }
  ]
}