{
  "repositories": [
    {
      "author": "kanaka",
      "name": "mal",
      "href": "https://github.com/kanaka/mal",
      "description": "mal - Make a Lisp",
      "language": "Swift",
      "stars": 3993,
      "forks": 788
    },
    {
      "author": "scinfu",
      "name": "SwiftSoup",
      "href": "https://github.com/scinfu/SwiftSoup",
      "description": "SwiftSoup: Pure Swift HTML Parser, with best of DOM, CSS, and jquery (Supports Linux, iOS, Mac, tvOS, watchOS)",
      "language": "Swift",
      "stars": 302,
      "forks": 22
    },
    {
      "author": "Kofktu",
      "name": "KUIPopOver",
      "href": "https://github.com/Kofktu/KUIPopOver",
      "description": "Easy to use PopOver in iOS",
      "language": "Swift",
      "stars": 306,
      "forks": 16
    },
    {
      "author": "younatics",
      "name": "MediaBrowser",
      "href": "https://github.com/younatics/MediaBrowser",
      "description": "🏞 A simple iOS photo and video browser with optional grid view, captions and selections written in Swift3.",
      "language": "Swift",
      "stars": 138,
      "forks": 16
    },
    {
      "author": "olucurious",
      "name": "Awesome-ARKit",
      "href": "https://github.com/olucurious/Awesome-ARKit",
      "description": "A curated list of awesome ARKit projects and resources. Feel free to contribute!",
      "language": "Swift",
      "stars": 2086,
      "forks": 162
    },
    {
      "author": "kingcos",
      "name": "WWDCHelper",
      "href": "https://github.com/kingcos/WWDCHelper",
      "description": "WWDCHelper & WWDC notes & code",
      "language": "Swift",
      "stars": 77,
      "forks": 6
    },
    {
      "author": "turbolinks",
      "name": "turbolinks-ios",
      "href": "https://github.com/turbolinks/turbolinks-ios",
      "description": "Native iOS adapter for building hybrid apps with Turbolinks 5",
      "language": "Swift",
      "stars": 575,
      "forks": 50
    },
    {
      "author": "mergesort",
      "name": "FeedbackEffect",
      "href": "https://github.com/mergesort/FeedbackEffect",
      "description": "A μ library for playing sounds and providing haptic feedback with ease",
      "language": "Swift",
      "stars": 138,
      "forks": 4
    },
    {
      "author": "AppliKeySolutions",
      "name": "VegaScroll",
      "href": "https://github.com/AppliKeySolutions/VegaScroll",
      "description": "VegaScroll is a lightweight animation flowlayout for UICollectionView completely written in Swift 4, compatible with iOS 11 and xCode 9.",
      "language": "Swift",
      "stars": 40,
      "forks": 2
    },
    {
      "author": "shadowsocks",
      "name": "ShadowsocksX-NG",
      "href": "https://github.com/shadowsocks/ShadowsocksX-NG",
      "description": "Next Generation of ShadowsocksX",
      "language": "Swift",
      "stars": 5521,
      "forks": 2068
    },
    {
      "author": "ReactiveX",
      "name": "RxSwift",
      "href": "https://github.com/ReactiveX/RxSwift",
      "description": "Reactive Programming in Swift",
      "language": "Swift",
      "stars": 10707,
      "forks": 1645
    },
    {
      "author": "malkouz",
      "name": "MKMagneticProgress",
      "href": "https://github.com/malkouz/MKMagneticProgress",
      "description": "A circular progress bar for iOS written in Swift",
      "language": "Swift",
      "stars": 41,
      "forks": 5
    },
    {
      "author": "WenchaoD",
      "name": "FSPagerView",
      "href": "https://github.com/WenchaoD/FSPagerView",
      "description": "FSPagerView is an elegant Screen Slide Library. It is extremely helpful for making Banner View、Product Show、Welcome/Guide Pages、Screen/ViewController Sliders.",
      "language": "Swift",
      "stars": 2029,
      "forks": 183
    },
    {
      "author": "ABTSoftware",
      "name": "SciChart.iOS.Examples",
      "href": "https://github.com/ABTSoftware/SciChart.iOS.Examples",
      "description": "Examples, Showcase & Tutorials for SciChart.iOS High Performance Charting Library",
      "language": "Swift",
      "stars": 41,
      "forks": 4
    },
    {
      "author": "Alamofire",
      "name": "Alamofire",
      "href": "https://github.com/Alamofire/Alamofire",
      "description": "Elegant HTTP Networking in Swift",
      "language": "Swift",
      "stars": 25164,
      "forks": 4372
    },
    {
      "author": "lkzhao",
      "name": "Hero",
      "href": "https://github.com/lkzhao/Hero",
      "description": "Elegant transition library for iOS & tvOS",
      "language": "Swift",
      "stars": 10381,
      "forks": 703
    },
    {
      "author": "realm",
      "name": "SwiftLint",
      "href": "https://github.com/realm/SwiftLint",
      "description": "A tool to enforce Swift style and conventions.",
      "language": "Swift",
      "stars": 7629,
      "forks": 655
    },
    {
      "author": "kdawgwilk",
      "name": "Autobahn",
      "href": "https://github.com/kdawgwilk/Autobahn",
      "description": "CLI tool written in Swift heavily inspired by https://github.com/fastlane/fastlane",
      "language": "Swift",
      "stars": 41,
      "forks": 2
    },
    {
      "author": "danielgindi",
      "name": "Charts",
      "href": "https://github.com/danielgindi/Charts",
      "description": "Beautiful charts for iOS/tvOS/OSX! The Apple side of the crossplatform MPAndroidChart.",
      "language": "Swift",
      "stars": 15752,
      "forks": 2917
    },
    {
      "author": "lhc70000",
      "name": "iina",
      "href": "https://github.com/lhc70000/iina",
      "description": "The modern video player for macOS.",
      "language": "Swift",
      "stars": 7764,
      "forks": 556
    },
    {
      "author": "Moya",
      "name": "Moya",
      "href": "https://github.com/Moya/Moya",
      "description": "Network abstraction layer written in Swift.",
      "language": "Swift",
      "stars": 6955,
      "forks": 771
    },
    {
      "author": "SwiftyJSON",
      "name": "SwiftyJSON",
      "href": "https://github.com/SwiftyJSON/SwiftyJSON",
      "description": "The better way to deal with JSON data in Swift",
      "language": "Swift",
      "stars": 15420,
      "forks": 2703
    },
    {
      "author": "vsouza",
      "name": "awesome-ios",
      "href": "https://github.com/vsouza/awesome-ios",
      "description": "A curated list of awesome iOS ecosystem, including Objective-C and Swift Projects",
      "language": "Swift",
      "stars": 21533,
      "forks": 3633
    },
    {
      "author": "dkhamsing",
      "name": "open-source-ios-apps",
      "href": "https://github.com/dkhamsing/open-source-ios-apps",
      "description": "📱 Collaborative List of Open-Source iOS Apps",
      "language": "Swift",
      "stars": 14258,
      "forks": 2521
    },
    {
      "author": "ashleymills",
      "name": "Reachability.swift",
      "href": "https://github.com/ashleymills/Reachability.swift",
      "description": "Replacement for Apple's Reachability re-written in Swift with closures",
      "language": "Swift",
      "stars": 4175,
      "forks": 479
    }
  ]
}