{
  "repositories": [
    {
      "author": "stascorp",
      "name": "rdpwrap",
      "href": "https://github.com/stascorp/rdpwrap",
      "description": "RDP Wrapper Library",
      "language": "Pascal",
      "stars": 4359,
      "forks": 705
    },
    {
      "author": "tedsmith",
      "name": "quickhash",
      "href": "https://github.com/tedsmith/quickhash",
      "description": "Graphical cross platform data hashing tool for Linux, Windows and Mac",
      "language": "Pascal",
      "stars": 106,
      "forks": 16
    },
    {
      "author": "me2d13",
      "name": "luamacros",
      "href": "https://github.com/me2d13/luamacros",
      "description": null,
      "language": "Pascal",
      "stars": 257,
      "forks": 35
    },
    {
      "author": "castle-engine",
      "name": "castle-engine",
      "href": "https://github.com/castle-engine/castle-engine",
      "description": "Cross-platform 3D and 2D game engine with a lot of graphic effects and a scene graph based on X3D",
      "language": "Pascal",
      "stars": 165,
      "forks": 33
    },
    {
      "author": "IndySockets",
      "name": "Indy",
      "href": "https://github.com/IndySockets/Indy",
      "description": "Indy - Internet Direct",
      "language": "Pascal",
      "stars": 55,
      "forks": 11
    },
    {
      "author": "cheat-engine",
      "name": "cheat-engine",
      "href": "https://github.com/cheat-engine/cheat-engine",
      "description": "Cheat Engine. A development environment focused on modding",
      "language": "Pascal",
      "stars": 2317,
      "forks": 521
    },
    {
      "author": "jrsoftware",
      "name": "issrc",
      "href": "https://github.com/jrsoftware/issrc",
      "description": "Inno Setup is a free installer for Windows programs. First introduced in 1997, Inno Setup today rivals and even surpasses many commercial installers in feature set and stability.",
      "language": "Pascal",
      "stars": 1274,
      "forks": 386
    },
    {
      "author": "ThomasJaeger",
      "name": "VisualMASM",
      "href": "https://github.com/ThomasJaeger/VisualMASM",
      "description": "Visual MASM - Assembly IDE for Microsoft MASM",
      "language": "Pascal",
      "stars": 1053,
      "forks": 35
    },
    {
      "author": "nodemcu",
      "name": "nodemcu-flasher",
      "href": "https://github.com/nodemcu/nodemcu-flasher",
      "description": "A firmware Flash tool for nodemcu",
      "language": "Pascal",
      "stars": 1004,
      "forks": 441
    },
    {
      "author": "HeidiSQL",
      "name": "HeidiSQL",
      "href": "https://github.com/HeidiSQL/HeidiSQL",
      "description": "A lightweight client for managing MySQL, MSSQL and PostgreSQL, written in Delphi",
      "language": "Pascal",
      "stars": 900,
      "forks": 100
    },
    {
      "author": "transmission-remote-gui",
      "name": "transgui",
      "href": "https://github.com/transmission-remote-gui/transgui",
      "description": "🧲 A feature rich cross platform Transmission BitTorrent client. Faster and has more functionality than the built-in web GUI.",
      "language": "Pascal",
      "stars": 881,
      "forks": 82
    },
    {
      "author": "prof7bit",
      "name": "TorChat",
      "href": "https://github.com/prof7bit/TorChat",
      "description": "Decentralized anonymous instant messenger on top of Tor Hidden Services",
      "language": "Pascal",
      "stars": 757,
      "forks": 254
    },
    {
      "author": "dfdragon",
      "name": "kcptun_gclient",
      "href": "https://github.com/dfdragon/kcptun_gclient",
      "description": "GUI for KCPTun windows client",
      "language": "Pascal",
      "stars": 739,
      "forks": 139
    },
    {
      "author": "Fr0sT-Brutal",
      "name": "awesome-delphi",
      "href": "https://github.com/Fr0sT-Brutal/awesome-delphi",
      "description": "A curated list of awesome Delphi frameworks, libraries, resources, and shiny things. Inspired by awesome-... stuff. Open source and freeware only!",
      "language": "Pascal",
      "stars": 603,
      "forks": 143
    },
    {
      "author": "t-d-k",
      "name": "LibreCrypt",
      "href": "https://github.com/t-d-k/LibreCrypt",
      "description": "LibreCrypt: Transparent on-the-fly disk encryption for Windows. LUKS compatible.",
      "language": "Pascal",
      "stars": 554,
      "forks": 58
    },
    {
      "author": "riderkick",
      "name": "FMD",
      "href": "https://github.com/riderkick/FMD",
      "description": "Forked from https://sf.net/p/fmd/",
      "language": "Pascal",
      "stars": 449,
      "forks": 94
    },
    {
      "author": "salvadordf",
      "name": "CEF4Delphi",
      "href": "https://github.com/salvadordf/CEF4Delphi",
      "description": "CEF4Delphi is an open source project to embed Chromium-based browsers in applications made with Delphi or Lazarus/FPC.",
      "language": "Pascal",
      "stars": 406,
      "forks": 128
    },
    {
      "author": "synopse",
      "name": "mORMot",
      "href": "https://github.com/synopse/mORMot",
      "description": "Synopse mORMot ORM/SOA/MVC framework",
      "language": "Pascal",
      "stars": 383,
      "forks": 189
    },
    {
      "author": "felipedaragon",
      "name": "sandcat",
      "href": "https://github.com/felipedaragon/sandcat",
      "description": "An open-source, pentest and developer-oriented web browser, using the power of Lua",
      "language": "Pascal",
      "stars": 373,
      "forks": 59
    },
    {
      "author": "MojtabaTajik",
      "name": "Robber",
      "href": "https://github.com/MojtabaTajik/Robber",
      "description": "Robber is open source tool for finding executables prone to DLL hijacking",
      "language": "Pascal",
      "stars": 366,
      "forks": 65
    },
    {
      "author": "RRUZ",
      "name": "delphi-ide-theme-editor",
      "href": "https://github.com/RRUZ/delphi-ide-theme-editor",
      "description": "Custom color highlighting for Object Pascal IDE's",
      "language": "Pascal",
      "stars": 364,
      "forks": 44
    },
    {
      "author": "pyscripter",
      "name": "pyscripter",
      "href": "https://github.com/pyscripter/pyscripter",
      "description": "Pyscripter is a feature-rich but lightweight Python IDE",
      "language": "Pascal",
      "stars": 355,
      "forks": 182
    },
    {
      "author": "project-jedi",
      "name": "jcl",
      "href": "https://github.com/project-jedi/jcl",
      "description": "JEDI Code Library",
      "language": "Pascal",
      "stars": 340,
      "forks": 204
    },
    {
      "author": "project-jedi",
      "name": "jvcl",
      "href": "https://github.com/project-jedi/jvcl",
      "description": "JEDI Visual Component Library",
      "language": "Pascal",
      "stars": 339,
      "forks": 208
    },
    {
      "author": "danieleteti",
      "name": "delphimvcframework",
      "href": "https://github.com/danieleteti/delphimvcframework",
      "description": "DMVCFramework (for short) is a popular and powerful framework for web solution in Delphi",
      "language": "Pascal",
      "stars": 335,
      "forks": 120
    }
  ]
}