{
  "repositories": [
    {
      "author": "yairm210",
      "name": "Unciv",
      "href": "https://github.com/yairm210/Unciv",
      "description": "Open-source Android/Desktop remake of Civ V",
      "language": "Kotlin",
      "stars": 421,
      "forks": 145,
      "starsInPeriod": 23
    },
    {
      "author": "nikhilpanju",
      "name": "FabFilter",
      "href": "https://github.com/nikhilpanju/FabFilter",
      "description": "Android app to showcase complex animations",
      "language": "Kotlin",
      "stars": 181,
      "forks": 28,
      "starsInPeriod": 32
    },
    {
      "author": "material-components",
      "name": "material-components-android-examples",
      "href": "https://github.com/material-components/material-components-android-examples",
      "description": "Companion example apps and code for MDC-Android.",
      "language": "Kotlin",
      "stars": 590,
      "forks": 68,
      "starsInPeriod": 10
    },
    {
      "author": "KasperskyLab",
      "name": "Kaspresso",
      "href": "https://github.com/KasperskyLab/Kaspresso",
      "description": "Great UI test framework",
      "language": "Kotlin",
      "stars": 485,
      "forks": 26,
      "starsInPeriod": 16
    },
    {
      "author": "rumboalla",
      "name": "apkupdater",
      "href": "https://github.com/rumboalla/apkupdater",
      "description": "APKUpdater is an open source tool that simplifies the process of finding updates for your installed apps.",
      "language": "Kotlin",
      "stars": 745,
      "forks": 98,
      "starsInPeriod": 4
    },
    {
      "author": "EmmyLua",
      "name": "IntelliJ-EmmyLua",
      "href": "https://github.com/EmmyLua/IntelliJ-EmmyLua",
      "description": "Lua IDE/Debugger Plugin for IntelliJ IDEA",
      "language": "Kotlin",
      "stars": 962,
      "forks": 150,
      "starsInPeriod": 7
    },
    {
      "author": "android",
      "name": "compose-samples",
      "href": "https://github.com/android/compose-samples",
      "description": null,
      "language": "Kotlin",
      "stars": 731,
      "forks": 99,
      "starsInPeriod": 13
    },
    {
      "author": "android",
      "name": "plaid",
      "href": "https://github.com/android/plaid",
      "description": "An Android app which provides design news & inspiration as well as being an example of implementing material design.",
      "language": "Kotlin",
      "stars": 14756,
      "forks": 3001,
      "starsInPeriod": 11
    },
    {
      "author": "android10",
      "name": "Android-CleanArchitecture-Kotlin",
      "href": "https://github.com/android10/Android-CleanArchitecture-Kotlin",
      "description": "This is a movies sample app in Kotlin, which is part of a serie of blog posts I have written about architecting android application using different approaches.",
      "language": "Kotlin",
      "stars": 2157,
      "forks": 427,
      "starsInPeriod": 6
    },
    {
      "author": "eycorsican",
      "name": "kitsunebi-android",
      "href": "https://github.com/eycorsican/kitsunebi-android",
      "description": "A fully-featured V2Ray client for Android.",
      "language": "Kotlin",
      "stars": 899,
      "forks": 161,
      "starsInPeriod": 2
    },
    {
      "author": "google-developer-training",
      "name": "android-kotlin-fundamentals-apps",
      "href": "https://github.com/google-developer-training/android-kotlin-fundamentals-apps",
      "description": "android-kotlin-fundamentals-apps",
      "language": "Kotlin",
      "stars": 196,
      "forks": 255,
      "starsInPeriod": 2
    },
    {
      "author": "airbnb",
      "name": "MvRx",
      "href": "https://github.com/airbnb/MvRx",
      "description": "MvRx: Android on Autopilot",
      "language": "Kotlin",
      "stars": 3428,
      "forks": 247,
      "starsInPeriod": 5
    },
    {
      "author": "android",
      "name": "architecture-samples",
      "href": "https://github.com/android/architecture-samples",
      "description": "A collection of samples to discuss and showcase different architectural tools and patterns for Android apps.",
      "language": "Kotlin",
      "stars": 35074,
      "forks": 9787,
      "starsInPeriod": 17
    },
    {
      "author": "ktorio",
      "name": "ktor",
      "href": "https://github.com/ktorio/ktor",
      "description": "Framework for quickly creating connected applications in Kotlin with minimal effort",
      "language": "Kotlin",
      "stars": 6032,
      "forks": 459,
      "starsInPeriod": 7
    },
    {
      "author": "duckduckgo",
      "name": "Android",
      "href": "https://github.com/duckduckgo/Android",
      "description": "DuckDuckGo Android App",
      "language": "Kotlin",
      "stars": 1100,
      "forks": 282,
      "starsInPeriod": 5
    },
    {
      "author": "alibaba",
      "name": "p3c",
      "href": "https://github.com/alibaba/p3c",
      "description": "Alibaba Java Coding Guidelines pmd implements and IDE plugin",
      "language": "Kotlin",
      "stars": 19617,
      "forks": 4803,
      "starsInPeriod": 37
    },
    {
      "author": "android",
      "name": "camera-samples",
      "href": "https://github.com/android/camera-samples",
      "description": "Multiple samples showing the best practices in camera APIs on Android.",
      "language": "Kotlin",
      "stars": 974,
      "forks": 474,
      "starsInPeriod": 6
    },
    {
      "author": "RocketChat",
      "name": "Rocket.Chat.Android",
      "href": "https://github.com/RocketChat/Rocket.Chat.Android",
      "description": "Rocket.Chat client in Kotlin for Android",
      "language": "Kotlin",
      "stars": 831,
      "forks": 567,
      "starsInPeriod": 0
    },
    {
      "author": "cashapp",
      "name": "sqldelight",
      "href": "https://github.com/cashapp/sqldelight",
      "description": "SQLDelight - Generates typesafe Kotlin APIs from SQL https://cashapp.github.io/sqldelight/",
      "language": "Kotlin",
      "stars": 2910,
      "forks": 220,
      "starsInPeriod": 5
    },
    {
      "author": "nhaarman",
      "name": "mockito-kotlin",
      "href": "https://github.com/nhaarman/mockito-kotlin",
      "description": "Using Mockito with Kotlin",
      "language": "Kotlin",
      "stars": 2070,
      "forks": 133,
      "starsInPeriod": 3
    },
    {
      "author": "android",
      "name": "databinding-samples",
      "href": "https://github.com/android/databinding-samples",
      "description": null,
      "language": "Kotlin",
      "stars": 926,
      "forks": 213,
      "starsInPeriod": 2
    },
    {
      "author": "InsertKoinIO",
      "name": "koin",
      "href": "https://github.com/InsertKoinIO/koin",
      "description": "Koin - a pragmatic lightweight dependency injection framework for Kotlin",
      "language": "Kotlin",
      "stars": 4682,
      "forks": 285,
      "starsInPeriod": 10
    },
    {
      "author": "arrow-kt",
      "name": "arrow",
      "href": "https://github.com/arrow-kt/arrow",
      "description": "Functional companion to Kotlin's Standard Library",
      "language": "Kotlin",
      "stars": 3181,
      "forks": 278,
      "starsInPeriod": 4
    },
    {
      "author": "m-zylab",
      "name": "SketchyComponent",
      "href": "https://github.com/m-zylab/SketchyComponent",
      "description": "A set of sketchy style components.",
      "language": "Kotlin",
      "stars": 98,
      "forks": 5,
      "starsInPeriod": 69
    },
    {
      "author": "Syex",
      "name": "MoviesMPP",
      "href": "https://github.com/Syex/MoviesMPP",
      "description": "Kotlin Multiplatform project with Clean Architecture, aiming to only implement the view natively.",
      "language": "Kotlin",
      "stars": 109,
      "forks": 14,
      "starsInPeriod": 11
    }
  ]
}